{"instance": "vrp-241", "num-variables": 551, "num-constraints": 757, "num-var-disjunct": 426, "max-disjunct": 4, "sum-disjunct": 1704, "values": [{"method": "RULT", "scans": 8.48731884057971, "cache-hits": 4683, "cache-misses": 81, "l1d-hits": 390882, "l1d-misses": 20168, "ll-read-hits": 3685, "ll-read-misses": 1, "ll-write-hits": 3685, "ll-write-misses": 1}, {"method": "ILP", "scans": 0.0, "cache-hits": 265731, "cache-misses": 17139, "l1d-hits": 14899839, "l1d-misses": 914456, "ll-read-hits": 113566, "ll-read-misses": 11849, "ll-write-hits": 113566, "ll-write-misses": 11849}, {"method": "BFDC", "scans": 3.675724637681159, "cache-hits": 1134, "cache-misses": 47, "l1d-hits": 158379, "l1d-misses": 12389, "ll-read-hits": 510, "ll-read-misses": 0, "ll-write-hits": 510, "ll-write-misses": 0}, {"method": "CRA", "scans": 6.1648550724637685, "cache-hits": 2113, "cache-misses": 139, "l1d-hits": 188560, "l1d-misses": 15465, "ll-read-hits": 632, "ll-read-misses": 1, "ll-write-hits": 632, "ll-write-misses": 1}]}