{"instance": "vrp-208", "num-variables": 360, "num-constraints": 560, "num-var-disjunct": 296, "max-disjunct": 10, "sum-disjunct": 2960, "values": [{"method": "RULT", "scans": 8.171745152354571, "cache-hits": 3072, "cache-misses": 58, "l1d-hits": 281610, "l1d-misses": 15780, "ll-read-hits": 1970, "ll-read-misses": 0, "ll-write-hits": 1970, "ll-write-misses": 0}, {"method": "ILP", "scans": 0.0, "cache-hits": 411829, "cache-misses": 18540, "l1d-hits": 32651529, "l1d-misses": 1713606, "ll-read-hits": 235420, "ll-read-misses": 16006, "ll-write-hits": 235420, "ll-write-misses": 16006}, {"method": "BFDC", "scans": 2.515235457063712, "cache-hits": 795, "cache-misses": 19, "l1d-hits": 71152, "l1d-misses": 5368, "ll-read-hits": 158, "ll-read-misses": 0, "ll-write-hits": 158, "ll-write-misses": 0}, {"method": "CRA", "scans": 17.797783933518005, "cache-hits": 3065, "cache-misses": 146, "l1d-hits": 417575, "l1d-misses": 30089, "ll-read-hits": 1348, "ll-read-misses": 2, "ll-write-hits": 1348, "ll-write-misses": 2}]}