{"instance": "vrp-114", "num-variables": 99, "num-constraints": 125, "num-var-disjunct": 90, "max-disjunct": 7, "sum-disjunct": 630, "values": [{"method": "RULT", "scans": 6.19, "cache-hits": 835, "cache-misses": 22, "l1d-hits": 53353, "l1d-misses": 2504, "ll-read-hits": 9, "ll-read-misses": 0, "ll-write-hits": 9, "ll-write-misses": 0}, {"method": "ILP", "scans": 0.0, "cache-hits": 121344, "cache-misses": 3355, "l1d-hits": 6978418, "l1d-misses": 307225, "ll-read-hits": 30194, "ll-read-misses": 3835, "ll-write-hits": 30194, "ll-write-misses": 3835}, {"method": "BFDC", "scans": 2.11, "cache-hits": 231, "cache-misses": 29, "l1d-hits": 16967, "l1d-misses": 502, "ll-read-hits": 4, "ll-read-misses": 0, "ll-write-hits": 4, "ll-write-misses": 0}, {"method": "CRA", "scans": 2.51, "cache-hits": 364, "cache-misses": 121, "l1d-hits": 12192, "l1d-misses": 536, "ll-read-hits": 1, "ll-read-misses": 0, "ll-write-hits": 1, "ll-write-misses": 0}]}