{"instance": "vrp-1", "num-variables": 40, "num-constraints": 54, "num-var-disjunct": 34, "max-disjunct": 16, "sum-disjunct": 544, "values": [{"method": "RULT", "scans": 8.048780487804878, "cache-hits": 558, "cache-misses": 8, "l1d-hits": 28678, "l1d-misses": 534, "ll-read-hits": 0, "ll-read-misses": 0, "ll-write-hits": 0, "ll-write-misses": 0}, {"method": "ILP", "scans": 0.0, "cache-hits": 102721, "cache-misses": 5290, "l1d-hits": 6444635, "l1d-misses": 253679, "ll-read-hits": 24141, "ll-read-misses": 3003, "ll-write-hits": 24141, "ll-write-misses": 3003}, {"method": "BFDC", "scans": 2.1219512195121952, "cache-hits": 166, "cache-misses": 27, "l1d-hits": 7294, "l1d-misses": 100, "ll-read-hits": 4, "ll-read-misses": 0, "ll-write-hits": 4, "ll-write-misses": 0}, {"method": "CRA", "scans": 10.78048780487805, "cache-hits": 236, "cache-misses": 107, "l1d-hits": 27396, "l1d-misses": 309, "ll-read-hits": 1, "ll-read-misses": 1, "ll-write-hits": 1, "ll-write-misses": 1}]}