{"instance": "vrp-50", "num-variables": 68, "num-constraints": 88, "num-var-disjunct": 53, "max-disjunct": 2, "sum-disjunct": 106, "values": [{"method": "RULT", "scans": 5.855072463768116, "cache-hits": 578, "cache-misses": 66, "l1d-hits": 31475, "l1d-misses": 976, "ll-read-hits": 4, "ll-read-misses": 0, "ll-write-hits": 4, "ll-write-misses": 0}, {"method": "ILP", "scans": 0.0, "cache-hits": 36869, "cache-misses": 2609, "l1d-hits": 1347817, "l1d-misses": 49059, "ll-read-hits": 7413, "ll-read-misses": 144, "ll-write-hits": 7413, "ll-write-misses": 144}, {"method": "BFDC", "scans": 2.710144927536232, "cache-hits": 127, "cache-misses": 24, "l1d-hits": 15379, "l1d-misses": 152, "ll-read-hits": 2, "ll-read-misses": 0, "ll-write-hits": 2, "ll-write-misses": 0}, {"method": "CRA", "scans": 2.710144927536232, "cache-hits": 196, "cache-misses": 38, "l1d-hits": 8392, "l1d-misses": 122, "ll-read-hits": 0, "ll-read-misses": 0, "ll-write-hits": 0, "ll-write-misses": 0}]}