{"instance": "vrp-72", "num-variables": 75, "num-constraints": 97, "num-var-disjunct": 65, "max-disjunct": 11, "sum-disjunct": 715, "values": [{"method": "RULT", "scans": 7.0, "cache-hits": 698, "cache-misses": 46, "l1d-hits": 47924, "l1d-misses": 2154, "ll-read-hits": 1, "ll-read-misses": 0, "ll-write-hits": 1, "ll-write-misses": 0}, {"method": "ILP", "scans": 0.0, "cache-hits": 118326, "cache-misses": 7937, "l1d-hits": 8270492, "l1d-misses": 370775, "ll-read-hits": 33505, "ll-read-misses": 5543, "ll-write-hits": 33505, "ll-write-misses": 5543}, {"method": "BFDC", "scans": 1.8157894736842106, "cache-hits": 234, "cache-misses": 47, "l1d-hits": 11485, "l1d-misses": 338, "ll-read-hits": 1, "ll-read-misses": 0, "ll-write-hits": 1, "ll-write-misses": 0}, {"method": "CRA", "scans": 3.473684210526316, "cache-hits": 225, "cache-misses": 112, "l1d-hits": 14400, "l1d-misses": 397, "ll-read-hits": 0, "ll-read-misses": 0, "ll-write-hits": 0, "ll-write-misses": 0}]}