{"instance": "vrp-108", "num-variables": 95, "num-constraints": 121, "num-var-disjunct": 66, "max-disjunct": 9, "sum-disjunct": 594, "values": [{"method": "RULT", "scans": 6.90625, "cache-hits": 781, "cache-misses": 61, "l1d-hits": 57520, "l1d-misses": 2534, "ll-read-hits": 3, "ll-read-misses": 0, "ll-write-hits": 3, "ll-write-misses": 0}, {"method": "ILP", "scans": 0.0, "cache-hits": 136355, "cache-misses": 4330, "l1d-hits": 6847766, "l1d-misses": 347901, "ll-read-hits": 32681, "ll-read-misses": 4292, "ll-write-hits": 32681, "ll-write-misses": 4292}, {"method": "BFDC", "scans": 2.5416666666666665, "cache-hits": 191, "cache-misses": 31, "l1d-hits": 20279, "l1d-misses": 420, "ll-read-hits": 1, "ll-read-misses": 0, "ll-write-hits": 1, "ll-write-misses": 0}, {"method": "CRA", "scans": 2.9895833333333335, "cache-hits": 415, "cache-misses": 67, "l1d-hits": 14493, "l1d-misses": 501, "ll-read-hits": 7, "ll-read-misses": 2, "ll-write-hits": 7, "ll-write-misses": 2}]}