{"instance": "vrp-172", "num-variables": 272, "num-constraints": 372, "num-var-disjunct": 231, "max-disjunct": 3, "sum-disjunct": 693, "values": [{"method": "RULT", "scans": 6.476190476190476, "cache-hits": 1591, "cache-misses": 57, "l1d-hits": 158082, "l1d-misses": 7183, "ll-read-hits": 1236, "ll-read-misses": 0, "ll-write-hits": 1236, "ll-write-misses": 0}, {"method": "ILP", "scans": 0.0, "cache-hits": 172439, "cache-misses": 9730, "l1d-hits": 7987237, "l1d-misses": 490301, "ll-read-hits": 51080, "ll-read-misses": 5342, "ll-write-hits": 51080, "ll-write-misses": 5342}, {"method": "BFDC", "scans": 2.249084249084249, "cache-hits": 644, "cache-misses": 4, "l1d-hits": 48053, "l1d-misses": 2578, "ll-read-hits": 33, "ll-read-misses": 0, "ll-write-hits": 33, "ll-write-misses": 0}, {"method": "CRA", "scans": 3.197802197802198, "cache-hits": 955, "cache-misses": 3, "l1d-hits": 43971, "l1d-misses": 3057, "ll-read-hits": 54, "ll-read-misses": 0, "ll-write-hits": 54, "ll-write-misses": 0}]}