{"instance": "grid-28", "num-variables": 97, "num-constraints": 597, "num-var-disjunct": 80, "max-disjunct": 10, "sum-disjunct": 800, "values": [{"method": "RULT", "scans": 5.020408163265306, "cache-hits": 1357, "cache-misses": 71, "l1d-hits": 47469, "l1d-misses": 2347, "ll-read-hits": 151, "ll-read-misses": 0, "ll-write-hits": 151, "ll-write-misses": 0}, {"method": "ILP", "scans": 0.0, "cache-hits": 45787, "cache-misses": 9272, "l1d-hits": 4516069, "l1d-misses": 161445, "ll-read-hits": 18417, "ll-read-misses": 3192, "ll-write-hits": 18417, "ll-write-misses": 3192}, {"method": "BFDC", "scans": 2.2857142857142856, "cache-hits": 369, "cache-misses": 10, "l1d-hits": 20545, "l1d-misses": 988, "ll-read-hits": 7, "ll-read-misses": 0, "ll-write-hits": 7, "ll-write-misses": 0}, {"method": "CRA", "scans": 8.173469387755102, "cache-hits": 756, "cache-misses": 68, "l1d-hits": 83989, "l1d-misses": 3362, "ll-read-hits": 6, "ll-read-misses": 0, "ll-write-hits": 6, "ll-write-misses": 0}]}