{"instance": "vrp-452", "num-variables": 73, "num-constraints": 95, "num-var-disjunct": 62, "max-disjunct": 8, "sum-disjunct": 496, "values": [{"method": "RULT", "scans": 5.905405405405405, "cache-hits": 704, "cache-misses": 10, "l1d-hits": 32318, "l1d-misses": 905, "ll-read-hits": 14, "ll-read-misses": 0, "ll-write-hits": 14, "ll-write-misses": 0}, {"method": "ILP", "scans": 0.0, "cache-hits": 33580, "cache-misses": 1250, "l1d-hits": 2595890, "l1d-misses": 92900, "ll-read-hits": 10141, "ll-read-misses": 958, "ll-write-hits": 10141, "ll-write-misses": 958}, {"method": "BFDC", "scans": 3.6216216216216215, "cache-hits": 165, "cache-misses": 6, "l1d-hits": 20628, "l1d-misses": 308, "ll-read-hits": 3, "ll-read-misses": 0, "ll-write-hits": 3, "ll-write-misses": 0}, {"method": "CRA", "scans": 4.175675675675675, "cache-hits": 309, "cache-misses": 73, "l1d-hits": 14561, "l1d-misses": 402, "ll-read-hits": 4, "ll-read-misses": 0, "ll-write-hits": 4, "ll-write-misses": 0}]}