{"instance": "vrp-667", "num-variables": 1343, "num-constraints": 1681, "num-var-disjunct": 984, "max-disjunct": 8, "sum-disjunct": 7872, "values": [{"method": "RULT", "scans": 5.833333333333333, "cache-hits": 5330, "cache-misses": 296, "l1d-hits": 666211, "l1d-misses": 35870, "ll-read-hits": 4573, "ll-read-misses": 7, "ll-write-hits": 4573, "ll-write-misses": 7}, {"method": "ILP", "scans": 0.0, "cache-hits": 240200, "cache-misses": 101649, "l1d-hits": 38027883, "l1d-misses": 1210844, "ll-read-hits": 183907, "ll-read-misses": 92545, "ll-write-hits": 183907, "ll-write-misses": 92545}, {"method": "BFDC", "scans": 2.8363095238095237, "cache-hits": 8297, "cache-misses": 65, "l1d-hits": 305128, "l1d-misses": 27657, "ll-read-hits": 7730, "ll-read-misses": 0, "ll-write-hits": 7730, "ll-write-misses": 0}, {"method": "CRA", "scans": 4.089285714285714, "cache-hits": 7786, "cache-misses": 570, "l1d-hits": 236899, "l1d-misses": 27887, "ll-read-hits": 7335, "ll-read-misses": 1, "ll-write-hits": 7335, "ll-write-misses": 1}]}