{"instance": "nc-28", "num-variables": 100, "num-constraints": 830, "num-var-disjunct": 80, "max-disjunct": 10, "sum-disjunct": 800, "values": [{"method": "RULT", "scans": 0.5148514851485149, "cache-hits": 322, "cache-misses": 65, "l1d-hits": 5016, "l1d-misses": 185, "ll-read-hits": 2, "ll-read-misses": 0, "ll-write-hits": 2, "ll-write-misses": 0}, {"method": "ILP", "scans": 0.0, "cache-hits": 41419, "cache-misses": 9815, "l1d-hits": 3741595, "l1d-misses": 138683, "ll-read-hits": 16611, "ll-read-misses": 3618, "ll-write-hits": 16611, "ll-write-misses": 3618}, {"method": "BFDC", "scans": 0.6534653465346535, "cache-hits": 229, "cache-misses": 46, "l1d-hits": 7666, "l1d-misses": 352, "ll-read-hits": 2, "ll-read-misses": 0, "ll-write-hits": 2, "ll-write-misses": 0}, {"method": "CRA", "scans": 0.1782178217821782, "cache-hits": 247, "cache-misses": 29, "l1d-hits": 3140, "l1d-misses": 189, "ll-read-hits": 0, "ll-read-misses": 0, "ll-write-hits": 0, "ll-write-misses": 0}]}